RocketSim.pyd
Cheese_RocketSim-1.2.0a7.dist-info/LICENSE
Cheese_RocketSim-1.2.0a7.dist-info/METADATA
Cheese_RocketSim-1.2.0a7.dist-info/WHEEL
Cheese_RocketSim-1.2.0a7.dist-info/top_level.txt
Cheese_RocketSim-1.2.0a7.dist-info/RECORD
