Metadata-Version: 2.1
Name: Cheese-RocketSim
Version: 1.2.0a7
Summary: A general package used in Rocket League Bots!
Home-page: UNKNOWN
License: UNKNOWN
Platform: UNKNOWN
License-File: LICENSE
